SystemdUnitParser/__init__.py
systemdunitparser-0.4.dist-info/licenses/LICENSE
systemdunitparser-0.4.dist-info/METADATA
systemdunitparser-0.4.dist-info/WHEEL
systemdunitparser-0.4.dist-info/top_level.txt
systemdunitparser-0.4.dist-info/RECORD
