Metadata-Version: 2.4
Name: systemdunitparser
Version: 0.4
Summary: Parser to read and create unit files for systemd
Author-email: Stephen Gallagher <sgallagh@redhat.com>
License: GPL-3.0-or-later
Project-URL: Homepage, http://github.com/sgallagher/systemdunitparser
Project-URL: Repository, http://github.com/sgallagher/systemdunitparser
Classifier: Intended Audience :: Developers
Classifier: Programming Language :: Python :: 3 :: Only
Requires-Python: >=3.9
License-File: LICENSE
Provides-Extra: test
Requires-Dist: pytest>=6.0; extra == "test"
Provides-Extra: dev
Requires-Dist: pytest>=6.0; extra == "dev"
Dynamic: license-file
